agoraiotools/AccessToken.py
agoraiotools/AccessToken2.py
agoraiotools/ChatTokenBuilder2.py
agoraiotools/DynamicKey.py
agoraiotools/DynamicKey2.py
agoraiotools/DynamicKey3.py
agoraiotools/DynamicKey4.py
agoraiotools/DynamicKey5.py
agoraiotools/Packer.py
agoraiotools/RtcTokenBuilder.py
agoraiotools/RtcTokenBuilder2.py
agoraiotools/RtmTokenBuilder.py
agoraiotools/RtmTokenBuilder2.py
agoraiotools/SignalingToken.py
agoraiotools/__init__.py
agoraiotools/_version.py
agoraiotools/apaas_token_builder.py
agoraiotools/education_token_builder.py
agoraiotools/fpa_token_builder.py
agoraiotools/utils.py
agoraiotools-0.3.4.dist-info/METADATA
agoraiotools-0.3.4.dist-info/WHEEL
agoraiotools-0.3.4.dist-info/licenses/LICENSE
agoraiotools-0.3.4.dist-info/RECORD
