Metadata-Version: 2.4
Name: agoraiotools
Version: 0.3.4
Summary: Agora token generation utilities
Project-URL: Homepage, https://github.com/AgoraIO/Tools
Project-URL: Source, https://github.com/AgoraIO/Tools
Author-email: Agora <developer@agora.io>
License: MIT
License-File: LICENSE
Requires-Python: >=3.8
